[{"s": "gboard-xiaomi-chto-eto", "t": "Gboard на Xiaomi: что это, как установить и настроить клавиатуру", "i": "📲", "c": "prilozheniya-i-servisy"}, {"s": "gboard-xiaomi-chto-eto-mozhno-li-udalit", "t": "Gboard на Xiaomi: что это, как удалить и заменить клавиатуру", "i": "📲", "c": "prilozheniya-i-servisy"}, {"s": "gboard-chto-eto-za-programma-na-xiaomi-redmi", "t": "Gboard на Xiaomi Redmi: что это за программа и как ей пользоваться", "i": "📲", "c": "prilozheniya-i-servisy"}, {"s": "gboard-chto-eto-za-programma-na-android-xiaomi", "t": "Gboard на Xiaomi: что это, настройки и функции", "i": "📲", "c": "prilozheniya-i-servisy"}, {"s": "gboard-chto-eto-za-programma-na-ksiomi", "t": "Gboard на Xiaomi: что это и как настроить клавиатуру", "i": "📁", "c": null}]